{
  "schemaVersion": 1,
  "fetchedAt": 1784142878324,
  "contentHash": "58acfde0f00b",
  "breaking": [
    {
      "title": "West Asia War LIVE: U.S. says 90-minute airstrikes target Greater Tunb Island, strategic point in Strait of Hormuz",
      "summary": "U.S. Central Command said the strikes further degraded Iran's ability to attack commercial shipping in the Strait of Hormuz",
      "source": "The Hindu International",
      "sourceGroup": "the_hindu",
      "url": "https://www.thehindu.com/news/international/west-asia-conflict-iran-us-war-washington-strikes-tehran-donald-trump-peace-deal-strait-of-hormuz-live-updates-july-15-2026/article71223849.ece",
      "publishedAt": 1784134446000,
      "category": "world",
      "region": "in",
      "language": "en",
      "id": "45a5c9ca27dd40dc",
      "suppressionReason": null,
      "isBreaking": true,
      "breakingScore": 6.805,
      "breakingReasons": [
        "severity_lexicon"
      ],
      "sourceCount": 1,
      "allSources": [
        "the_hindu"
      ],
      "firstSeen": 1784124231000
    },
    {
      "title": "Landslide Cuts Off Village Near China Border As Arunachal Floods Wreak Havoc",
      "summary": "Mechuka is a globally known tourist spot, visited by hundreds of tourists.",
      "source": "NDTV",
      "sourceGroup": "ndtv",
      "url": "https://www.ndtv.com/india-news/landslide-cuts-off-village-near-china-border-as-arunachal-floods-wreak-havoc-11776235#publisher=newsstand",
      "publishedAt": 1784129867000,
      "category": "topStories",
      "region": "in",
      "language": "en",
      "id": "4dfc0952b2baa204",
      "suppressionReason": null,
      "isBreaking": true,
      "breakingScore": 3.699,
      "breakingReasons": [
        "severity_lexicon"
      ],
      "sourceCount": 1,
      "allSources": [
        "ndtv"
      ],
      "firstSeen": 1784129867000
    },
    {
      "title": "Russian attacks kill eight as Ukraine hits Black Sea oil tankers",
      "summary": "Civilian casualties are reported in four Ukrainian regions, while Kyiv hits 20 Russian vessels in the Black Sea.",
      "source": "BBC World",
      "sourceGroup": "bbc",
      "url": "https://www.bbc.co.uk/news/articles/c8929jv8kdzo?at_medium=RSS&at_campaign=rss",
      "publishedAt": 1784122325000,
      "category": "world",
      "region": "in",
      "language": "en",
      "id": "8da2bbb7a374c8d5",
      "suppressionReason": null,
      "isBreaking": true,
      "breakingScore": 3.524,
      "breakingReasons": [
        "severity_lexicon"
      ],
      "sourceCount": 1,
      "allSources": [
        "bbc"
      ],
      "firstSeen": 1784122325000
    },
    {
      "title": "Right to die: French Parliament approves assisted dying bill after years of debate",
      "summary": "<img align=\"left\" border=\"0\" hspace=\"10\" src=\"https://timesofindia.indiatimes.com/photo/132422380.cms\" style=\"margin-top: 3px; margin-right: 5px;\" />",
      "source": "Times of India",
      "sourceGroup": "times_of_india",
      "url": "https://timesofindia.indiatimes.com/world/europe/right-to-die-french-parliament-approves-assisted-dying-bill-after-years-of-debate/articleshow/132422380.cms",
      "publishedAt": 1784137862000,
      "category": "india",
      "region": "in",
      "language": "en",
      "id": "18169bc1875597af",
      "suppressionReason": null,
      "isBreaking": true,
      "breakingScore": 2.884,
      "breakingReasons": [
        "multi_source_velocity"
      ],
      "sourceCount": 2,
      "allSources": [
        "bbc",
        "times_of_india"
      ],
      "firstSeen": 1784136566000
    },
    {
      "title": "Nagercoil custodial death: Eight prison inmates arrested in connection with Sabari Varman’s death",
      "summary": "With the post mortem report revealing injuries on his body, the police have alerted the case of suspicious death to that of murder. However, the motive for the murder was still being probed",
      "source": "The Hindu",
      "sourceGroup": "the_hindu",
      "url": "https://www.thehindu.com/news/cities/Madurai/nagercoil-custodial-death-eight-prison-inmates-arrested-in-connection-with-sabari-varmans-death/article71226426.ece",
      "publishedAt": 1784141296000,
      "category": "topStories",
      "region": "in",
      "language": "en",
      "id": "70118383409790f5",
      "suppressionReason": null,
      "isBreaking": true,
      "breakingScore": 2.463,
      "breakingReasons": [
        "severity_lexicon"
      ],
      "sourceCount": 1,
      "allSources": [
        "the_hindu"
      ],
      "firstSeen": 1784141296000
    },
    {
      "title": "Cauvery is not a flood discharge channel for Karnataka to open at will, say farmers",
      "summary": "Hundreds of farmers march to border against Mekadatu project",
      "source": "The Hindu",
      "sourceGroup": "the_hindu",
      "url": "https://www.thehindu.com/news/cities/Coimbatore/cauvery-is-not-a-flood-discharge-channel-for-karnataka-to-open-at-will-say-farmers/article71225696.ece",
      "publishedAt": 1784141212000,
      "category": "topStories",
      "region": "in",
      "language": "en",
      "id": "550133bd76aaf0c0",
      "suppressionReason": null,
      "isBreaking": true,
      "breakingScore": 2.461,
      "breakingReasons": [
        "severity_lexicon"
      ],
      "sourceCount": 1,
      "allSources": [
        "the_hindu"
      ],
      "firstSeen": 1784141212000
    },
    {
      "title": "Iran threatens to block more trade routes as US launches fresh strikes",
      "summary": "US President Donald Trump vowed to strike Iran's bridges and power plants next week if the country does not return to talks.",
      "source": "BBC World",
      "sourceGroup": "bbc",
      "url": "https://www.bbc.co.uk/news/articles/c9323zgq6wvo?at_medium=RSS&at_campaign=rss",
      "publishedAt": 1784140881000,
      "category": "world",
      "region": "in",
      "language": "en",
      "id": "78b0f3cca7ef1adf",
      "suppressionReason": null,
      "isBreaking": true,
      "breakingScore": 2.454,
      "breakingReasons": [
        "severity_lexicon"
      ],
      "sourceCount": 1,
      "allSources": [
        "bbc"
      ],
      "firstSeen": 1784140881000
    },
    {
      "title": "Tasmac employees observe hunger strike urging government to fulfil charter of demands",
      "summary": "",
      "source": "The Hindu",
      "sourceGroup": "the_hindu",
      "url": "https://www.thehindu.com/news/cities/Madurai/tasmac-employees-observe-hunger-strike-urging-government-to-fulfil-charter-of-demands/article71227193.ece",
      "publishedAt": 1784139896000,
      "category": "topStories",
      "region": "in",
      "language": "en",
      "id": "f0b93d91e2c27899",
      "suppressionReason": null,
      "isBreaking": true,
      "breakingScore": 2.431,
      "breakingReasons": [
        "severity_lexicon"
      ],
      "sourceCount": 1,
      "allSources": [
        "the_hindu"
      ],
      "firstSeen": 1784139896000
    }
  ]
}